dimit/__init__.py
dimit/__version__.py
dimit/core.py
dimit-0.0.5.dist-info/LICENSE
dimit-0.0.5.dist-info/METADATA
dimit-0.0.5.dist-info/WHEEL
dimit-0.0.5.dist-info/top_level.txt
dimit-0.0.5.dist-info/RECORD
