Metadata-Version: 2.1
Name: dimit
Version: 0.0.5
Summary: Dimension of a quantity in Python language.
Home-page: https://github.com/pboymt/dimit
Author: pboymt
Author-email: pboymt@foxmail.com
License: GNU GENERAL PUBLIC LICENSE
Platform: UNKNOWN
Classifier: License :: OSI Approved :: GNU General Public License v3 (GPLv3)
Classifier: Operating System :: OS Independent
Classifier: Programming Language :: Python
Classifier: Programming Language :: Python :: 3
Classifier: Programming Language :: Python :: 3.9
Classifier: Programming Language :: Python :: 3.10
Classifier: Programming Language :: Python :: Implementation :: CPython
Classifier: Programming Language :: Python :: Implementation :: PyPy
License-File: LICENSE
